fingertips_py/__init__.py
fingertips_py/api_calls.py
fingertips_py/area_data.py
fingertips_py/metadata.py
fingertips_py/retrieve_data.py
fingertips_py-0.4.2.dist-info/LICENSE
fingertips_py-0.4.2.dist-info/METADATA
fingertips_py-0.4.2.dist-info/WHEEL
fingertips_py-0.4.2.dist-info/top_level.txt
fingertips_py-0.4.2.dist-info/RECORD
