Metadata-Version: 2.1
Name: fingertips_py
Version: 0.4.2
Summary: This is a python package to interact with OHID Fingertips data tool. This can be used to load data from the Fingertips API into Python for further manipulation.
Author: Russell Plunkett, Annabel Westermann, Hadley Nanayakkara, Olivia Box Power
Maintainer-email: DHSC <DataScience@dhsc.gov.uk>
License:                     GNU GENERAL PUBLIC LICENSE
Project-URL: Homepage, https://github.com/ukhsa-collaboration/PHDS_fingertips_py?tab=readme-ov-file
Project-URL: Documentation, https://fingertips-py.readthedocs.io/en/latest/
Project-URL: Repository, https://github.com/ukhsa-collaboration/PHDS_fingertips_py
Project-URL: Issues, https://github.com/ukhsa-collaboration/PHDS_fingertips_py/issues
Project-URL: Changelog, https://github.com/ukhsa-collaboration/PHDS_fingertips_py/blob/master/CHANGELOG.md
Keywords: DHSC,Department of Health and Social Care,OHID,Office for Health Improvement and Disparities,Public Health,indicators,Fingertips
Classifier: Development Status :: 4 - Beta
Classifier: Programming Language :: Python :: 3
Classifier: Operating System :: OS Independent
Requires-Python: >=3.8
License-File: LICENSE
Requires-Dist: pandas>=1.5
Requires-Dist: requests
